faster_whisper_hotkey/__init__.py
faster_whisper_hotkey/__main__.py
faster_whisper_hotkey/available_models_languages.json
faster_whisper_hotkey/clipboard.py
faster_whisper_hotkey/config.py
faster_whisper_hotkey/models.py
faster_whisper_hotkey/paste.py
faster_whisper_hotkey/settings.py
faster_whisper_hotkey/terminal.py
faster_whisper_hotkey/transcribe.py
faster_whisper_hotkey/transcriber.py
faster_whisper_hotkey/ui.py
faster_whisper_hotkey-0.4.3.dist-info/licenses/LICENSE.txt
faster_whisper_hotkey-0.4.3.dist-info/METADATA
faster_whisper_hotkey-0.4.3.dist-info/WHEEL
faster_whisper_hotkey-0.4.3.dist-info/entry_points.txt
faster_whisper_hotkey-0.4.3.dist-info/top_level.txt
faster_whisper_hotkey-0.4.3.dist-info/RECORD
