Metadata-Version: 2.4
Name: faster-whisper-hotkey
Version: 0.4.3
Summary: Push-to-talk transcription
Author: blakkd
Keywords: keyboard,recognition,voice,typing,speech,shortcut,speech-to-text,hotkey,stt,asr,faster-whisper,whisper,parakeet,canary,voxtral
Classifier: Programming Language :: Python :: 3
Classifier: Operating System :: POSIX
Requires-Python: >=3.10
License-File: LICENSE.txt
Requires-Dist: sounddevice
Requires-Dist: numpy
Requires-Dist: faster-whisper
Requires-Dist: pynput
Requires-Dist: pulsectl
Requires-Dist: torch
Requires-Dist: nemo_toolkit[asr]
Requires-Dist: requests
Requires-Dist: importlib_resources
Requires-Dist: mistral-common[audio]>=1.8.4
Requires-Dist: transformers>=4.56
Requires-Dist: bitsandbytes>=0.43.1
Requires-Dist: pyperclip
Dynamic: license-file
